fastapi_jwt_auth/__init__.py
fastapi_jwt_auth/auth_config.py
fastapi_jwt_auth/auth_jwt.py
fastapi_jwt_auth/config.py
fastapi_jwt_auth/exceptions.py
fastapi_jwt_auth/py.typed
fastapi_jwt_auth_v2-0.1.4.dist-info/LICENSE
fastapi_jwt_auth_v2-0.1.4.dist-info/METADATA
fastapi_jwt_auth_v2-0.1.4.dist-info/WHEEL
fastapi_jwt_auth_v2-0.1.4.dist-info/RECORD
