Metadata-Version: 2.1
Name: fastapi-jwt-auth-v2
Version: 0.1.4
Summary: 
Author: Daniel Chico
Author-email: chico@generalsoftwareinc.com
Requires-Python: >=3.12,<4.0
Classifier: Programming Language :: Python :: 3
Classifier: Programming Language :: Python :: 3.12
Requires-Dist: fastapi (==0.*)
Requires-Dist: pyjwt (>=2.8.0,<3.0.0)
